javelin/__init__.py
javelin/__main__.py
javelin/utils/__init__.py
javelin/utils/aws.py
javelin/utils/github.py
javelin/utils/slack.py
javelin_cli-0.10.0.dist-info/WHEEL
javelin_cli-0.10.0.dist-info/METADATA
javelin_cli-0.10.0.dist-info/RECORD
